DecisionTree/Hardware_ ipcore/decision_tree.v
// ============================================================================
// ============================================================================

// ============================================================================
// MODULE 1: INPUT FEATURE SCALER (IMPROVED)
// ============================================================================
module feature_scaler (
    input  wire        clk,              // Thêm clock để pipeline
    input  wire        rst_n,
    input  wire        valid_in,         // Input valid signal
    input  wire [10:0] arb_id_dec,
    input  wire [3:0]  data_length,
    input  wire [7:0]  first_byte,
    input  wire [7:0]  last_byte,
    input  wire [10:0] byte_sum,
    input  wire [31:0] time_delta,
    
    output reg  [31:0] feature_0_scaled,
    output reg  [31:0] feature_1_scaled,
    output reg  [31:0] feature_2_scaled,
    output reg  [31:0] feature_3_scaled,
    output reg  [31:0] feature_4_scaled,
    output reg  [31:0] feature_5_scaled,
    output reg         valid_out         // Output valid signal
);

    // Pipeline registers để tránh timing violations
    reg [31:0] f0_comb, f1_comb, f2_comb, f3_comb, f4_comb, f5_comb;
    
    // Combinational scaling
    always @(*) begin
        // Feature 0: arb_id_dec - Q11.16
        f0_comb = {21'b0, arb_id_dec} << 16;
        
        // Feature 1: data_length - Q4.23
        f1_comb = {28'b0, data_length} << 23;
        
        // Feature 2: first_byte - Q8.19
        f2_comb = {24'b0, first_byte} << 19;
        
        // Feature 3: last_byte - Q8.19
        f3_comb = {24'b0, last_byte} << 19;
        
        // Feature 4: byte_sum - Q11.16
        f4_comb = {21'b0, byte_sum} << 16;
        
        // Feature 5: time_delta - Q0.27
        // Sử dụng phép nhân thay vì chia để tránh latency cao
        // time_delta (us) * 2^27 / 1000000 ≈ time_delta * 134
        f5_comb = (time_delta * 134);  // Approximate scaling
    end
    
    // Sequential output để đồng bộ timing
    always @(posedge clk or negedge rst_n) begin
        if (!rst_n) begin
            feature_0_scaled <= 32'b0;
            feature_1_scaled <= 32'b0;
            feature_2_scaled <= 32'b0;
            feature_3_scaled <= 32'b0;
            feature_4_scaled <= 32'b0;
            feature_5_scaled <= 32'b0;
            valid_out <= 1'b0;
        end else if (valid_in) begin
            feature_0_scaled <= f0_comb;
            feature_1_scaled <= f1_comb;
            feature_2_scaled <= f2_comb;
            feature_3_scaled <= f3_comb;
            feature_4_scaled <= f4_comb;
            feature_5_scaled <= f5_comb;
            valid_out <= 1'b1;
        end else begin
            valid_out <= 1'b0;
        end
    end

endmodule


// ============================================================================
// MODULE 2: FEATURE SELECTOR (IMPROVED)
// ============================================================================
module feature_selector (
    input  wire        clk,
    input  wire        rst_n,
    input  wire        valid_in,
    input  wire [2:0]  feature_id,
    input  wire [31:0] feature_0_scaled,
    input  wire [31:0] feature_1_scaled,
    input  wire [31:0] feature_2_scaled,
    input  wire [31:0] feature_3_scaled,
    input  wire [31:0] feature_4_scaled,
    input  wire [31:0] feature_5_scaled,
    output reg  [31:0] selected_feature,
    output reg         valid_out,
    output reg         error             // Invalid feature_id
);

    always @(posedge clk or negedge rst_n) begin
        if (!rst_n) begin
            selected_feature <= 32'b0;
            valid_out <= 1'b0;
            error <= 1'b0;
        end else if (valid_in) begin
            error <= 1'b0;
            valid_out <= 1'b1;
            case (feature_id)
                3'd0: selected_feature <= feature_0_scaled;
                3'd1: selected_feature <= feature_1_scaled;
                3'd2: selected_feature <= feature_2_scaled;
                3'd3: selected_feature <= feature_3_scaled;
                3'd4: selected_feature <= feature_4_scaled;
                3'd5: selected_feature <= feature_5_scaled;
                default: begin
                    selected_feature <= 32'b0;
                    error <= 1'b1;  // Invalid feature ID
                end
            endcase
        end else begin
            valid_out <= 1'b0;
        end
    end

endmodule


// ============================================================================
// MODULE 3: THRESHOLD COMPARATOR (IMPROVED)
// ============================================================================
module threshold_comparator (
    input  wire        clk,
    input  wire        rst_n,
    input  wire        valid_in,
    input  wire [31:0] feature_value,
    input  wire [26:0] threshold_raw,
    output reg         go_left,
    output reg         valid_out
);

    wire [31:0] threshold_extended;
    assign threshold_extended = {5'b0, threshold_raw};
    
    // Pipeline comparison để cải thiện timing
    always @(posedge clk or negedge rst_n) begin
        if (!rst_n) begin
            go_left <= 1'b0;
            valid_out <= 1'b0;
        end else if (valid_in) begin
            go_left <= (feature_value <= threshold_extended);
            valid_out <= 1'b1;
        end else begin
            valid_out <= 1'b0;
        end
    end

endmodule


// ============================================================================
// MODULE 4: NODE DECODER (IMPROVED - Combinational, no changes needed)
// ============================================================================
module node_decoder (
    input  wire [63:0] node_data,
    output wire [7:0]  node_id,
    output wire [2:0]  feature_id,
    output wire [26:0] threshold,
    output wire [7:0]  right_child,
    output wire [7:0]  left_child,
    output wire [7:0]  node_type,
    output wire        is_leaf
);

    assign node_id     = node_data[63:56];
    assign feature_id  = node_data[55:53];
    assign threshold   = node_data[52:26];
    assign right_child = node_data[25:18];
    assign left_child  = node_data[17:10];
    assign node_type   = node_data[9:2];
    
    assign is_leaf = (node_type == 8'h01) || 
                     ((left_child == 8'h00) && (right_child == 8'h00));

endmodule


// ============================================================================
// MODULE 5: DECISION TREE TRAVERSAL (IMPROVED)
// ============================================================================
module decision_tree_classifier (
    input  wire        clk,
    input  wire        rst_n,
    input  wire        start,
    
    // Input: Raw CAN message data
    input  wire [10:0] arb_id_dec,
    input  wire [3:0]  data_length,
    input  wire [7:0]  first_byte,
    input  wire [7:0]  last_byte,
    input  wire [10:0] byte_sum,
    input  wire [31:0] time_delta,
    
    // Output: Classification result
    output reg         done,
    output reg         is_attack,
    output reg  [7:0]  final_node,
    output reg         error,            // Error flag
    output reg  [7:0]  tree_depth        // Độ sâu của cây (debug)
);

    // ========================================================================
    // STATE MACHINE - Cải thiện với thêm states
    // ========================================================================
    localparam IDLE         = 3'd0;
    localparam SCALE        = 3'd1;
    localparam DECODE       = 3'd2;
    localparam COMPARE      = 3'd3;
    localparam NEXT_NODE    = 3'd4;
    localparam CLASSIFY     = 3'd5;
    localparam ERROR_STATE  = 3'd6;
    
    reg [2:0] state, next_state;
    reg [7:0] current_node_addr;
    reg [7:0] depth_counter;
    
    // Max depth protection (tránh infinite loop)
    localparam MAX_DEPTH = 8'd50;
    
    // ========================================================================
    // TREE MEMORY
    // ========================================================================
    reg [63:0] tree_mem [0:172];
    
    initial begin
        $readmemb("tree.mem", tree_mem);
    end
    
    wire [63:0] current_node_data;
    assign current_node_data = tree_mem[current_node_addr];
    
    // ========================================================================
    // PIPELINE CONTROL SIGNALS
    // ========================================================================
    reg        scale_valid;
    wire       scale_done;
    reg        selector_valid;
    wire       selector_done;
    wire       selector_error;
    reg        compare_valid;
    wire       compare_done;
    
    // ========================================================================
    // FEATURE SCALING - Pipelined
    // ========================================================================
    wire [31:0] feature_0_scaled, feature_1_scaled, feature_2_scaled;
    wire [31:0] feature_3_scaled, feature_4_scaled, feature_5_scaled;
    
    feature_scaler scaler (
        .clk(clk),
        .rst_n(rst_n),
        .valid_in(scale_valid),
        .arb_id_dec(arb_id_dec),
        .data_length(data_length),
        .first_byte(first_byte),
        .last_byte(last_byte),
        .byte_sum(byte_sum),
        .time_delta(time_delta),
        .feature_0_scaled(feature_0_scaled),
        .feature_1_scaled(feature_1_scaled),
        .feature_2_scaled(feature_2_scaled),
        .feature_3_scaled(feature_3_scaled),
        .feature_4_scaled(feature_4_scaled),
        .feature_5_scaled(feature_5_scaled),
        .valid_out(scale_done)
    );
    
    // ========================================================================
    // NODE DECODING
    // ========================================================================
    wire [7:0]  node_id;
    wire [2:0]  feature_id;
    wire [26:0] threshold;
    wire [7:0]  right_child, left_child;
    wire [7:0]  node_type;
    wire        is_leaf;
    
    node_decoder decoder (
        .node_data(current_node_data),
        .node_id(node_id),
        .feature_id(feature_id),
        .threshold(threshold),
        .right_child(right_child),
        .left_child(left_child),
        .node_type(node_type),
        .is_leaf(is_leaf)
    );
    
    // ========================================================================
    // FEATURE SELECTION - Pipelined
    // ========================================================================
    wire [31:0] selected_feature;
    
    feature_selector selector (
        .clk(clk),
        .rst_n(rst_n),
        .valid_in(selector_valid),
        .feature_id(feature_id),
        .feature_0_scaled(feature_0_scaled),
        .feature_1_scaled(feature_1_scaled),
        .feature_2_scaled(feature_2_scaled),
        .feature_3_scaled(feature_3_scaled),
        .feature_4_scaled(feature_4_scaled),
        .feature_5_scaled(feature_5_scaled),
        .selected_feature(selected_feature),
        .valid_out(selector_done),
        .error(selector_error)
    );
    
    // ========================================================================
    // THRESHOLD COMPARISON - Pipelined
    // ========================================================================
    wire go_left;
    
    threshold_comparator comparator (
        .clk(clk),
        .rst_n(rst_n),
        .valid_in(compare_valid),
        .feature_value(selected_feature),
        .threshold_raw(threshold),
        .go_left(go_left),
        .valid_out(compare_done)
    );
    
    // ========================================================================
    // NEXT NODE SELECTION
    // ========================================================================
    wire [7:0] next_node;
    assign next_node = go_left ? left_child : right_child;
    
    // ========================================================================
    // STATE MACHINE LOGIC - Improved
    // ========================================================================
    always @(posedge clk or negedge rst_n) begin
        if (!rst_n) begin
            state <= IDLE;
            current_node_addr <= 8'd0;
            depth_counter <= 8'd0;
            done <= 1'b0;
            is_attack <= 1'b0;
            final_node <= 8'd0;
            error <= 1'b0;
            tree_depth <= 8'd0;
            scale_valid <= 1'b0;
            selector_valid <= 1'b0;
            compare_valid <= 1'b0;
        end
        else begin
            // Default: clear one-cycle pulses
            scale_valid <= 1'b0;
            selector_valid <= 1'b0;
            compare_valid <= 1'b0;
            
            case (state)
                IDLE: begin
                    done <= 1'b0;
                    error <= 1'b0;
                    if (start) begin
                        current_node_addr <= 8'd0;
                        depth_counter <= 8'd0;
                        scale_valid <= 1'b1;  // Bắt đầu scaling
                        state <= SCALE;
                    end
                end
                
                SCALE: begin
                    if (scale_done) begin
                        state <= DECODE;
                    end
                end
                
                DECODE: begin
                    // Check if leaf node
                    if (is_leaf) begin
                        state <= CLASSIFY;
                        final_node <= current_node_addr;
                        tree_depth <= depth_counter;
                        is_attack <= (node_type == 8'h01);
                    end
                    else begin
                        // Check max depth
                        if (depth_counter >= MAX_DEPTH) begin
                            state <= ERROR_STATE;
                            error <= 1'b1;
                        end
                        else begin
                            selector_valid <= 1'b1;
                            state <= COMPARE;
                        end
                    end
                end
                
                COMPARE: begin
                    if (selector_done) begin
                        if (selector_error) begin
                            state <= ERROR_STATE;
                            error <= 1'b1;
                        end
                        else begin
                            compare_valid <= 1'b1;
                            state <= NEXT_NODE;
                        end
                    end
                end
                
                NEXT_NODE: begin
                    if (compare_done) begin
                        current_node_addr <= next_node;
                        depth_counter <= depth_counter + 1'b1;
                        state <= DECODE;
                    end
                end
                
                CLASSIFY: begin
                    done <= 1'b1;
                    state <= IDLE;
                end
                
                ERROR_STATE: begin
                    done <= 1'b1;
                    error <= 1'b1;
                    state <= IDLE;
                end
                
                default: state <= IDLE;
            endcase
        end
    end

endmodule


// ============================================================================
// TESTBENCH - IMPROVED
// ============================================================================
module tb_decision_tree;

    reg clk, rst_n, start;
    reg [10:0] arb_id_dec;
    reg [3:0]  data_length;
    reg [7:0]  first_byte, last_byte;
    reg [10:0] byte_sum;
    reg [31:0] time_delta;
    
    wire done, is_attack, error;
    wire [7:0] final_node, tree_depth;
    
    decision_tree_classifier dut (
        .clk(clk),
        .rst_n(rst_n),
        .start(start),
        .arb_id_dec(arb_id_dec),
        .data_length(data_length),
        .first_byte(first_byte),
        .last_byte(last_byte),
        .byte_sum(byte_sum),
        .time_delta(time_delta),
        .done(done),
        .is_attack(is_attack),
        .final_node(final_node),
        .error(error),
        .tree_depth(tree_depth)
    );
    
    // Clock generation: 10ns period (100MHz)
    initial clk = 0;
    always #5 clk = ~clk;
    
    // Timeout watchdog
    initial begin
        #100000;
        $display("ERROR: Simulation timeout!");
        $finish;
    end
    
    // Test stimulus
    initial begin
        $dumpfile("dt_classifier.vcd");
        $dumpvars(0, tb_decision_tree);
        
        // Initialize
        rst_n = 0;
        start = 0;
        arb_id_dec = 0;
        data_length = 0;
        first_byte = 0;
        last_byte = 0;
        byte_sum = 0;
        time_delta = 0;
        
        #20 rst_n = 1;
        #10;
        
        // Test case 1: Normal message
        $display("\n=== Test 1: Normal Message ===");
        @(posedge clk);
   arb_id_dec  = 11'd0;
   data_length = 5'd16;
   first_byte  = 8'd0;
   last_byte   = 8'd0;
   byte_sum    = 11'd0;
   time_delta  = 32'd0; // microseconds
        start = 1;
        @(posedge clk);
        start = 0;
        
        wait(done);
        if (!error)
            $display("Result: Node=%d, Attack=%b, Depth=%d", 
                     final_node, is_attack, tree_depth);
        else
            $display("ERROR in classification!");
        
        #100;
        $display("\n=== All tests completed ===");
        $finish;
    end
    
    // Monitor signals
    always @(posedge clk) begin
        if (done && !error) begin
            $display("  [%0t] Classification complete", $time);
        end
        if (error) begin
            $display("  [%0t] ERROR detected!", $time);
        end
    end

endmodule

DecisionTree/Hardware_ ipcore/dt_classifier.vcd
$date
	Tue Nov 11 21:46:54 2025
$end
$version
	Icarus Verilog
$end
$timescale
	1s
$end
$scope module tb_decision_tree $end
$var wire 8 ! tree_depth [7:0] $end
$var wire 1 " is_attack $end
$var wire 8 # final_node [7:0] $end
$var wire 1 $ error $end
$var wire 1 % done $end
$var reg 11 & arb_id_dec [10:0] $end
$var reg 11 ' byte_sum [10:0] $end
$var reg 1 ( clk $end
$var reg 4 ) data_length [3:0] $end
$var reg 8 * first_byte [7:0] $end
$var reg 8 + last_byte [7:0] $end
$var reg 1 , rst_n $end
$var reg 1 - start $end
$var reg 32 . time_delta [31:0] $end
$scope module dut $end
$var wire 11 / arb_id_dec [10:0] $end
$var wire 11 0 byte_sum [10:0] $end
$var wire 1 ( clk $end
$var wire 64 1 current_node_data [63:0] $end
$var wire 4 2 data_length [3:0] $end
$var wire 8 3 first_byte [7:0] $end
$var wire 8 4 last_byte [7:0] $end
$var wire 1 , rst_n $end
$var wire 1 - start $end
$var wire 32 5 time_delta [31:0] $end
$var wire 27 6 threshold [26:0] $end
$var wire 1 7 selector_error $end
$var wire 1 8 selector_done $end
$var wire 32 9 selected_feature [31:0] $end
$var wire 1 : scale_done $end
$var wire 8 ; right_child [7:0] $end
$var wire 8 < node_type [7:0] $end
$var wire 8 = node_id [7:0] $end
$var wire 8 > next_node [7:0] $end
$var wire 8 ? left_child [7:0] $end
$var wire 1 @ is_leaf $end
$var wire 1 A go_left $end
$var wire 3 B feature_id [2:0] $end
$var wire 32 C feature_5_scaled [31:0] $end
$var wire 32 D feature_4_scaled [31:0] $end
$var wire 32 E feature_3_scaled [31:0] $end
$var wire 32 F feature_2_scaled [31:0] $end
$var wire 32 G feature_1_scaled [31:0] $end
$var wire 32 H feature_0_scaled [31:0] $end
$var wire 1 I compare_done $end
$var parameter 3 J CLASSIFY $end
$var parameter 3 K COMPARE $end
$var parameter 3 L DECODE $end
$var parameter 3 M ERROR_STATE $end
$var parameter 3 N IDLE $end
$var parameter 8 O MAX_DEPTH $end
$var parameter 3 P NEXT_NODE $end
$var parameter 3 Q SCALE $end
$var reg 1 R compare_valid $end
$var reg 8 S current_node_addr [7:0] $end
$var reg 8 T depth_counter [7:0] $end
$var reg 1 % done $end
$var reg 1 $ error $end
$var reg 8 U final_node [7:0] $end
$var reg 1 " is_attack $end
$var reg 1 V scale_valid $end
$var reg 1 W selector_valid $end
$var reg 3 X state [2:0] $end
$var reg 8 Y tree_depth [7:0] $end
$scope module comparator $end
$var wire 1 ( clk $end
$var wire 1 , rst_n $end
$var wire 1 R valid_in $end
$var wire 27 Z threshold_raw [26:0] $end
$var wire 32 [ threshold_extended [31:0] $end
$var wire 32 \ feature_value [31:0] $end
$var reg 1 A go_left $end
$var reg 1 I valid_out $end
$upscope $end
$scope module decoder $end
$var wire 1 @ is_leaf $end
$var wire 64 ] node_data [63:0] $end
$var wire 27 ^ threshold [26:0] $end
$var wire 8 _ right_child [7:0] $end
$var wire 8 ` node_type [7:0] $end
$var wire 8 a node_id [7:0] $end
$var wire 8 b left_child [7:0] $end
$var wire 3 c feature_id [2:0] $end
$upscope $end
$scope module scaler $end
$var wire 11 d arb_id_dec [10:0] $end
$var wire 11 e byte_sum [10:0] $end
$var wire 1 ( clk $end
$var wire 4 f data_length [3:0] $end
$var wire 8 g first_byte [7:0] $end
$var wire 8 h last_byte [7:0] $end
$var wire 1 , rst_n $end
$var wire 32 i time_delta [31:0] $end
$var wire 1 V valid_in $end
$var reg 32 j f0_comb [31:0] $end
$var reg 32 k f1_comb [31:0] $end
$var reg 32 l f2_comb [31:0] $end
$var reg 32 m f3_comb [31:0] $end
$var reg 32 n f4_comb [31:0] $end
$var reg 32 o f5_comb [31:0] $end
$var reg 32 p feature_0_scaled [31:0] $end
$var reg 32 q feature_1_scaled [31:0] $end
$var reg 32 r feature_2_scaled [31:0] $end
$var reg 32 s feature_3_scaled [31:0] $end
$var reg 32 t feature_4_scaled [31:0] $end
$var reg 32 u feature_5_scaled [31:0] $end
$var reg 1 : valid_out $end
$upscope $end
$scope module selector $end
$var wire 1 ( clk $end
$var wire 32 v feature_0_scaled [31:0] $end
$var wire 32 w feature_1_scaled [31:0] $end
$var wire 32 x feature_2_scaled [31:0] $end
$var wire 32 y feature_3_scaled [31:0] $end
$var wire 32 z feature_4_scaled [31:0] $end
$var wire 32 { feature_5_scaled [31:0] $end
$var wire 3 | feature_id [2:0] $end
$var wire 1 , rst_n $end
$var wire 1 W valid_in $end
$var reg 1 7 error $end
$var reg 32 } selected_feature [31:0] $end
$var reg 1 8 valid_out $end
$upscope $end
$upscope $end
$upscope $end
$enddefinitions $end
$comment Show the parameter values. $end
$dumpall
b1 Q
b100 P
b110010 O
b0 N
b110 M
b10 L
b11 K
b101 J
$end
#0
$dumpvars
b0 }
b0 |
b0 {
b0 z
b0 y
b0 x
b0 w
b0 v
b0 u
b0 t
b0 s
b0 r
b0 q
b0 p
b0 o
b0 n
b0 m
b0 l
b0 k
b0 j
b0 i
b0 h
b0 g
b0 f
b0 e
b0 d
b0 c
b1 b
b0 a
b0 `
b10 _
b101111011000000000000000 ^
b10111101100000000000000000000010000000010000000000 ]
b0 \
b101111011000000000000000 [
b101111011000000000000000 Z
b0 Y
b0 X
0W
0V
b0 U
b0 T
b0 S
0R
0I
b0 H
b0 G
b0 F
b0 E
b0 D
b0 C
b0 B
0A
0@
b1 ?
b10 >
b0 =
b0 <
b10 ;
0:
b0 9
08
07
b101111011000000000000000 6
b0 5
b0 4
b0 3
b0 2
b10111101100000000000000000000010000000010000000000 1
b0 0
b0 /
b0 .
0-
0,
b0 +
b0 *
b0 )
0(
b0 '
b0 &
0%
0$
b0 #
0"
b0 !
$end
#5
1(
#10
0(
#15
1(
#20
0(
1,
#25
1(
#30
0(
#35
b1 X
1V
1-
1(
#40
0(
#45
0V
1:
0-
1(
#50
0(
#55
0:
b10 X
1(
#60
0(
#65
b11 X
1W
1(
#70
0(
#75
18
0W
1(
#80
0(
#85
b100 X
1R
08
1(
#90
0(
#95
b1 >
1I
1A
0R
1(
#100
0(
#105
b11 >
b1 =
b1 a
b1101100111000000000000000 [
b1101100111000000000000000 6
b1101100111000000000000000 Z
b1101100111000000000000000 ^
b100 ;
b100 _
b11 ?
b11 b
b10 X
b1 T
b100000110110011100000000000000000000100000000110000000000 1
b100000110110011100000000000000000000100000000110000000000 ]
b1 S
0I
1(
#110
0(
#115
b11 X
1W
1(
#120
0(
#125
0W
18
1(
#130
0(
#135
08
b100 X
1R
1(
#140
0(
#145
0R
1I
1(
#150
0(
#155
b1011001 >
b11 =
b11 a
b1011011 [
b1011011 6
b1011011 Z
b1011011 ^
b1011010 ;
b1011010 _
b1011001 ?
b1011001 b
0I
b10 X
b10 T
b1100000000000000000000000101101101011010010110010000000000 1
b1100000000000000000000000101101101011010010110010000000000 ]
b11 S
1(
#160
0(
#165
b11 X
1W
1(
#170
0(
#175
18
0W
1(
#180
0(
#185
b100 X
1R
08
1(
#190
0(
#195
1I
0R
1(
#200
0(
#205
b1110011 >
b1011001 =
b1011001 a
b101000000000000000 [
b101000000000000000 6
b101000000000000000 Z
b101000000000000000 ^
b1110100 ;
b1110100 _
b1110011 ?
b1110011 b
b10 X
b11 T
b101100100000000000010100000000000000001110100011100110000000000 1
b101100100000000000010100000000000000001110100011100110000000000 ]
b1011001 S
0I
1(
#210
0(
#215
b11 X
1W
1(
#220
0(
#225
0W
18
1(
#230
0(
#235
08
b100 X
1R
1(
#240
0(
#245
0R
1I
1(
#250
0(
#255
b1111111 >
b1110011 =
b1110011 a
b1011101000000000000000 [
b1011101000000000000000 6
b1011101000000000000000 Z
b1011101000000000000000 ^
b10000000 ;
b10000000 _
b1111111 ?
b1111111 b
0I
b10 X
b100 T
b111001100000000101110100000000000000010000000011111110000000000 1
b111001100000000101110100000000000000010000000011111110000000000 ]
b1110011 S
1(
#260
0(
#265
b11 X
1W
1(
#270
0(
#275
18
0W
1(
#280
0(
#285
b100 X
1R
08
1(
#290
0(
#295
1I
0R
1(
#300
0(
#305
b10000001 >
b1111111 =
b1111111 a
b1000101 [
b1000101 6
b1000101 Z
b1000101 ^
b10000010 ;
b10000010 _
b10000001 ?
b10000001 b
b10 X
b101 T
b111111100000000000000000000000100010110000010100000010000000000 1
b111111100000000000000000000000100010110000010100000010000000000 ]
b1111111 S
0I
1(
#310
0(
#315
b11 X
1W
1(
#320
0(
#325
0W
18
1(
#330
0(
#335
08
b100 X
1R
1(
#340
0(
#345
0R
1I
1(
#350
0(
#355
b10000011 >
b10000001 =
b10000001 a
b1 [
b1 6
b1 Z
b1 ^
b10000100 ;
b10000100 _
b10000011 ?
b10000011 b
0I
b10 X
b110 T
b1000000100000000000000000000000000000110000100100000110000000000 1
b1000000100000000000000000000000000000110000100100000110000000000 ]
b10000001 S
1(
#360
0(
#365
b11 X
1W
1(
#370
0(
#375
18
0W
1(
#380
0(
#385
b100 X
1R
08
1(
#390
0(
#395
1I
0R
1(
#400
0(
#405
b0 >
1@
b10000011 =
b10000011 a
b0 [
b0 6
b0 Z
b0 ^
b0 ;
b0 _
b0 ?
b0 b
b1 <
b1 `
b10 X
b111 T
b1000001100000000000000000000000000000000000000000000000000000100 1
b1000001100000000000000000000000000000000000000000000000000000100 ]
b10000011 S
0I
1(
#410
0(
#415
1"
b111 !
b111 Y
b10000011 #
b10000011 U
b101 X
1(
#420
0(
#425
b0 X
1%
1(
#430
0(
#435
0%
1(
